{
  "new_messages_one": "eine neue Nachricht hier",
  "new_messages_other": "{{count}} neue Nachrichten hier",
  "seconds_one": "sekunde",
  "seconds_other": "sekunden",
  "minutes_one": "minute",
  "minutes_other": "minuten",
  "hours_one": "stunde",
  "hours_other": "stunden",
  "days_one": "tag",
  "days_other": "tage",
  "weeks_one": "woche",
  "weeks_other": "wochen",
  "months_one": "monat",
  "months_other": "monate",
  "years_one": "jahr",
  "years_other": "jahre",
  "count-seconds_one": "{{count}} sekunde",
  "count-seconds_other": "{{count}} sekunden",
  "count-weeks_one": "{{count}} woche",
  "count-weeks_other": "{{count}} wochen",
  "count-months_one": "{{count}} monat",
  "count-months_other": "{{count}} monate",
  "count-years_one": "{{count}} jahr",
  "count-years_other": "{{count}} jahre",
  "january": "Januar",
  "february": "Februar",
  "march": "März",
  "april": "April",
  "may": "Mai",
  "june": "Juni",
  "july": "Juli",
  "august": "August",
  "september": "September",
  "october": "Oktober",
  "november": "November",
  "december": "Dezember",
  "today": "Heute",
  "tomorrow": "Morgen",
  "yesterday": "Gestern",
  "today_lower": "heute",
  "tomorrow_lower": "morgen",
  "yesterday_lower": "gestern",
  "sunday-short": "So",
  "monday-short": "Mo",
  "tuesday-short": "Di",
  "wednesday-short": "Wir",
  "thursday-short": "Do",
  "friday-short": "Fr",
  "saturday-short": "Sa",
  "fabiux": {
    "nested1": {
      "nested2": {
        "key1": "value 1",
        "key2": "value 2"
      }
    }
  }
}